{
  "mushroom_id": "rusoli",
  "scientific_name": "Russula olivacea",
  "common_name": "Olive Russula",
  "edibility": "E",
  "description": "Olive Russula has olive-brown to olive-green cap (5-12 cm), sticky. Gills yellowish. Stem white. KEY: OLIVE CAP color, BRITTLE FLESH, yellowish gills. Flesh white. Spore print ochre. Mild to slightly acrid.",
  "habitat": "Mycorrhizal with hardwoods, especially beech and oak. Grows on ground in deciduous forests. European species. Scattered.",
  "season": "Summer through fall (July-October).",
  "regions": [
    "Europe",
    "Eastern US"
  ],
  "lookalikes": [
    "Other olive/green Russulas",
    "Lactarius - have LATEX"
  ],
  "safety_notes": "EDIBLE: Mild flavor. OLIVE CAP + YELLOW GILLS + BRITTLE FLESH diagnostic. Taste test (mild specimens edible). Cook thoroughly.",
  "images": [
    {
      "index": 0,
      "source_url": "https://mushroomobserver.org/images/640/1701271.jpg",
      "photographer": "Drew Henderson",
      "license_url": "http://creativecommons.org/licenses/by-sa/3.0/",
      "observation_date": "2024-08-29",
      "file_size_bytes": 51876,
      "width": 640,
      "height": 480,
      "sha256": "eb7533cc54577cdab5f8186a7e1e490bec9fe45de25dd08c41d4e93d2e90dd9f"
    },
    {
      "index": 1,
      "source_url": "https://mushroomobserver.org/images/640/1701268.jpg",
      "photographer": "Drew Henderson",
      "license_url": "http://creativecommons.org/licenses/by-sa/3.0/",
      "observation_date": "2024-08-27",
      "file_size_bytes": 51182,
      "width": 480,
      "height": 640,
      "sha256": "d756050d1f956f660f1ffd5c22bdaa3aa87bd59532fd3b83547b298269d7a780"
    }
  ],
  "content_version": "2.0",
  "last_updated": "2025-11-10T11:18:57.376636"
}