{
  "mushroom_id": "ruscas",
  "scientific_name": "Russula cascadensis",
  "common_name": "Cascade Russula",
  "edibility": "E",
  "description": "Cascade Russula has white cap (5-15 cm), becoming yellowish with age. Gills white, crowded. Stem white, thick. KEY: BRITTLE FLESH, NO LATEX, large white mushroom, Pacific Northwest. Flesh white. Spore print white. Mild taste.",
  "habitat": "Mycorrhizal with CONIFERS in Pacific Northwest, especially Douglas fir, hemlock, true firs. Grows on ground in coniferous forests. Regional endemic. Scattered or groups.",
  "season": "Fall (September-November), fruiting after fall rains.",
  "regions": [
    "Pacific Northwest",
    "British Columbia",
    "Northern California"
  ],
  "lookalikes": [
    "Russula brevipes - very similar",
    "Other white Russulas",
    "Lactarius - have LATEX"
  ],
  "safety_notes": "EDIBLE: Mild flavor. WHITE CAP + BRITTLE FLESH + NO LATEX + PNW CONIFERS diagnostic. Taste test confirms. Cook thoroughly.",
  "images": [
    {
      "index": 0,
      "source_url": "https://mushroomobserver.org/images/640/1515362.jpg",
      "photographer": "Joe Mat",
      "license_url": "http://creativecommons.org/licenses/by-sa/3.0/",
      "observation_date": "2022-10-14",
      "file_size_bytes": 96106,
      "width": 640,
      "height": 480,
      "sha256": "80a360b89bb292bf9e445025b2536932d8451eae663609d677c69e8fe42cf3c5"
    },
    {
      "index": 1,
      "source_url": "https://mushroomobserver.org/images/640/1515363.jpg",
      "photographer": "Joe Mat",
      "license_url": "http://creativecommons.org/licenses/by-sa/3.0/",
      "observation_date": "2022-10-14",
      "file_size_bytes": 120372,
      "width": 640,
      "height": 480,
      "sha256": "e1665ef87b0306cd7f9dc949b407a33a50feffb6cf95dfcd8508cd4ea3aa9131"
    }
  ],
  "content_version": "2.0",
  "last_updated": "2025-11-07T22:00:00.000000"
}